MANIFEST.in
README.rst
setup.py
cloudhub/__init__.py
cloudhub/application.py
cloudhub/cli.py
cloudhub/common.py
cloudhub/legacy.py
cloudhub/maven.py
cloudhub/notification.py
cloudhub/root.py
pycloudhub.egg-info/PKG-INFO
pycloudhub.egg-info/SOURCES.txt
pycloudhub.egg-info/dependency_links.txt
pycloudhub.egg-info/entry_points.txt
pycloudhub.egg-info/requires.txt
pycloudhub.egg-info/top_level.txt