Metadata-Version: 1.1
Name: pycloudhub
Version: 0.1.9
Summary: A CloudHub API wrapper written in python
Home-page: https://bitbucket.org/pgolec/pycloudhub
Author: Patrick Golec
Author-email: pgolec+pypi@gmail.com
License: BSD
Keywords: cloud cloudhub mule mulesoft
Platform: UNKNOWN
Classifier: Development Status :: 3 - Alpha
Classifier: Environment :: Console
Classifier: Environment :: Other Environment
Classifier: Intended Audience :: Developers
Classifier: Intended Audience :: System Administrators
Classifier: Topic :: System :: Software Distribution
Classifier: Topic :: System :: Systems Administration
Classifier: License :: OSI Approved :: BSD License
Classifier: Programming Language :: Python :: 2
Classifier: Programming Language :: Python :: 2.7
Classifier: Programming Language :: Python :: 3
Classifier: Programming Language :: Python :: 3.4
Classifier: Programming Language :: Python :: 3.5
